dewi_commands/__init__.py
dewi_commands/commands/__init__.py
dewi_commands/commands/checksums/__init__.py
dewi_commands/commands/checksums/__main__.py
dewi_commands/commands/checksums/commands.py
dewi_commands/commands/collect_images/__init__.py
dewi_commands/commands/collect_images/__main__.py
dewi_commands/commands/deduplicate_images/__init__.py
dewi_commands/commands/deduplicate_images/__main__.py
dewi_commands/commands/dice/__init__.py
dewi_commands/commands/dice/__main__.py
dewi_commands/commands/dice/die.py
dewi_commands/commands/edit/__init__.py
dewi_commands/commands/edit/__main__.py
dewi_commands/commands/edit/edit.py
dewi_commands/commands/fetchcovidhu/__init__.py
dewi_commands/commands/fetchcovidhu/__main__.py
dewi_commands/commands/fetchcovidhu/fetch.py
dewi_commands/commands/filesync/__init__.py
dewi_commands/commands/filesync/__main__.py
dewi_commands/commands/find/__init__.py
dewi_commands/commands/find/__main__.py
dewi_commands/commands/find/find.py
dewi_commands/commands/hash/__init__.py
dewi_commands/commands/hash/__main__.py
dewi_commands/commands/http/__init__.py
dewi_commands/commands/http/__main__.py
dewi_commands/commands/jsonformatter/__init__.py
dewi_commands/commands/jsonformatter/__main__.py
dewi_commands/commands/license/__init__.py
dewi_commands/commands/license/__main__.py
dewi_commands/commands/lithurgical/__init__.py
dewi_commands/commands/lithurgical/__main__.py
dewi_commands/commands/packt/__init__.py
dewi_commands/commands/packt/__main__.py
dewi_commands/commands/packt/config.py
dewi_commands/commands/packt/packt.py
dewi_commands/commands/packt/runner.py
dewi_commands/commands/packt/utils.py
dewi_commands/commands/primes/__init__.py
dewi_commands/commands/primes/__main__.py
dewi_commands/commands/safe_delete_images/__init__.py
dewi_commands/commands/safe_delete_images/__main__.py
dewi_commands/commands/select_images/__init__.py
dewi_commands/commands/select_images/__main__.py
dewi_commands/commands/shell/__init__.py
dewi_commands-3.1.0.dist-info/COPYING
dewi_commands-3.1.0.dist-info/METADATA
dewi_commands-3.1.0.dist-info/WHEEL
dewi_commands-3.1.0.dist-info/top_level.txt
dewi_commands-3.1.0.dist-info/zip-safe
dewi_commands-3.1.0.dist-info/RECORD
